lndb_schema_wetlab/__init__.py
lndb_schema_wetlab/_core.py
lndb_schema_wetlab-0.1.2.dist-info/LICENSE
lndb_schema_wetlab-0.1.2.dist-info/WHEEL
lndb_schema_wetlab-0.1.2.dist-info/METADATA
lndb_schema_wetlab-0.1.2.dist-info/RECORD
