Metadata-Version: 2.1
Name: lndb_schema_wetlab
Version: 0.1.2
Summary: Wetlab schema module.
Author-email: Lamin Labs <laminlabs@gmail.com>
Requires-Dist: nbproject
Requires-Dist: lndb_schema_bionty
Requires-Dist: pre-commit ; extra == "dev"
Requires-Dist: nox ; extra == "dev"
Requires-Dist: pytest>=6.0 ; extra == "test"
Requires-Dist: pytest-cov ; extra == "test"
Project-URL: Home, https://github.com/laminlabs/lndb-schema-wetlab
Provides-Extra: dev
Provides-Extra: test
